termscraper/__init__.py
termscraper/__main__.py
termscraper/charsets.py
termscraper/control.py
termscraper/escape.py
termscraper/graphics.py
termscraper/modes.py
termscraper/screens.py
termscraper/streams.py
termscraper/version.py
termscraper-0.10.0.data/data/LICENSE
termscraper-0.10.0.dist-info/AUTHORS
termscraper-0.10.0.dist-info/LICENSE
termscraper-0.10.0.dist-info/METADATA
termscraper-0.10.0.dist-info/WHEEL
termscraper-0.10.0.dist-info/top_level.txt
termscraper-0.10.0.dist-info/RECORD
