Metadata-Version: 2.1
Name: termscraper
Version: 0.10.0
Summary: Simple VTXXX-compatible terminal emulator scraper.
Home-page: https://github.com/byexamples/termscraper
Author: Di Paola Martin
Author-email: use-github-issues@example.com
License: GNU LGPLv3
Keywords: scraper,pyte,vt102,vte,terminal emulator
Platform: any
Classifier: Development Status :: 5 - Production/Stable
Classifier: Environment :: Console
Classifier: Intended Audience :: Developers
Classifier: Operating System :: OS Independent
Classifier: License :: OSI Approved :: GNU Lesser General Public License v3 (LGPLv3)
Classifier: Programming Language :: Python :: 3.7
Classifier: Programming Language :: Python :: 3.8
Classifier: Programming Language :: Python :: 3.9
Classifier: Programming Language :: Python :: Implementation :: CPython
Classifier: Programming Language :: Python :: Implementation :: PyPy
Classifier: Topic :: Terminals :: Terminal Emulators/X Terminals
Requires-Python: >=3.6
Requires-Dist: wcwidth (==0.2.5)
